lookml_zenml/__init__.py
lookml_zenml/cli.py
lookml_zenml/lookml_models.py
lookml_zenml/lookml_project.py
lookml_zenml-0.3.2.dist-info/LICENSE
lookml_zenml-0.3.2.dist-info/METADATA
lookml_zenml-0.3.2.dist-info/WHEEL
lookml_zenml-0.3.2.dist-info/entry_points.txt
lookml_zenml-0.3.2.dist-info/RECORD
