Metadata-Version: 2.1
Name: lookml-zenml
Version: 0.3.2
Summary: 
Author: Paul Blankley
Author-email: paul@zenlytic.com
Requires-Python: >=3.9,<3.12
Classifier: Programming Language :: Python :: 3
Classifier: Programming Language :: Python :: 3.9
Classifier: Programming Language :: Python :: 3.10
Classifier: Programming Language :: Python :: 3.11
Requires-Dist: PyYAML (>=6.0,<7.0)
Requires-Dist: click (>=8.0,<9.0)
Requires-Dist: lkml (>=1.3.1,<2.0.0)
Requires-Dist: pydantic (>=2.11.7,<3.0.0)
Requires-Dist: ruamel.yaml (>=0.17.32,<0.18.0)
